odoo/addons/ssi_m2o_configurator_mixin/README.rst
odoo/addons/ssi_m2o_configurator_mixin/__init__.py
odoo/addons/ssi_m2o_configurator_mixin/__manifest__.py
odoo/addons/ssi_m2o_configurator_mixin/models/__init__.py
odoo/addons/ssi_m2o_configurator_mixin/models/mixin_many2one_configurator.py
odoo/addons/ssi_m2o_configurator_mixin/static/description/icon.png
odoo14_addon_ssi_m2o_configurator_mixin-14.0.2.1.0.dist-info/METADATA
odoo14_addon_ssi_m2o_configurator_mixin-14.0.2.1.0.dist-info/WHEEL
odoo14_addon_ssi_m2o_configurator_mixin-14.0.2.1.0.dist-info/top_level.txt
odoo14_addon_ssi_m2o_configurator_mixin-14.0.2.1.0.dist-info/RECORD
